<?xml version="1.0" encoding="UTF-8"?>
<objects serializationModel="Studio.02.02.00">
	<object class="Workspace" id="{7e624032-ead4-4463-8562-a03f4d2823bf}">
		<relationship name="masterEventFolder">
			<destination>{047d6fa9-b3cd-46e6-b180-97feb8f29ef5}</destination>
		</relationship>
		<relationship name="masterTagFolder">
			<destination>{1143078b-e3d6-4aa7-bdc6-9aeb15633a17}</destination>
		</relationship>
		<relationship name="masterEffectPresetFolder">
			<destination>{a9f48c93-2901-4d0b-9261-6646681537aa}</destination>
		</relationship>
		<relationship name="masterParameterPresetFolder">
			<destination>{58d34333-a266-4c15-bd6e-ec95858b96e6}</destination>
		</relationship>
		<relationship name="masterBankFolder">
			<destination>{13990771-23c4-424d-81f9-ef518047d5a8}</destination>
		</relationship>
		<relationship name="masterSandboxFolder">
			<destination>{d0e2e900-29f1-4985-9f4d-0897317a6962}</destination>
		</relationship>
		<relationship name="masterAssetFolder">
			<destination>{e7e51583-d683-4fde-a0ee-6e43aa95f058}</destination>
		</relationship>
		<relationship name="mixer">
			<destination>{8b1c57e5-6dee-48a7-91f6-01dec8056bf5}</destination>
		</relationship>
		<relationship name="profilerSessionFolder">
			<destination>{21057e4f-8622-4404-81c5-1c31a46c6cd9}</destination>
		</relationship>
		<relationship name="platforms">
			<destination>{8718545e-840f-48ba-beae-cf6266e46adc}</destination>
		</relationship>
	</object>
</objects>
